{
    "jerk": 23,
    "omg": 14,
    "oops": 6,
    "man": 5,
    "wow": 7,
    "freak": 6,
    "wicked": 8,
    "stupid": 6,
    "repels": 8,
    "impossible": 8,
    "1": 5,
    "ppl": 8,
    "kill": 11,
    "base": 5,
    "time": 6,
    "killed": 5,
    "yeah,": 15,
    "weasels": 19,
    "levi": 9,
    "team": 15,
    "death": 6,
    "weasel": 10,
    "guy": 5,
    "troll": 15,
    "minute": 5,
    "levis": 6,
    "freq": 7,
    "4": 8,
    "3": 6,
    "dogecoin": 10,
    "game": 8,
    "targeting": 5,
    "sundrop": 5,
    "kewl": 6,
    "kills": 6,
    "ship": 5,
    "evil": 6
}