{
    "hahaha": 130,
    "haha": 121,
    "sup sup": 92,
    "too easy": 82,
    "gg": 60,
    "stfu": 52,
    "lol": 33,
    "boom": 21,
    "aww": 17,
    "glhf": 13,
    "wtf": 20,
    "cya": 21,
    "hahahaha": 10,
    "retard": 29,
    "no team": 9,
    "yeah": 21,
    "true": 7,
    "hi donn": 7,
    "fuck": 18,
    "retards": 13,
    "ahahaha": 7,
    "booring": 7,
    "i dont miss": 7,
    "1": 7,
    "lool": 6,
    "lmao": 6,
    "?": 6,
    "learn to play": 6,
    "come on": 6,
    "nice try": 6,
    "hahah": 10,
    "hi david": 5,
    ":d": 12,
    "cool": 11,
    "ez": 6,
    "omg": 5,
    "easy": 19,
    "good": 42,
    "-b1": 5,
    "sick": 9,
    "ott": 9,
    "pussy": 7,
    "nice": 7,
    "duel": 10,
    "ben": 10,
    "dont": 36,
    "lose": 5,
    "wow": 7,
    "gay": 5,
    "ofc": 6,
    "basing": 5,
    "wuf": 12,
    "fun": 6,
    "5": 5,
    "terrier": 6,
    "hit": 5,
    "ha": 13,
    "train": 5,
    "feel": 8,
    "didnt": 10,
    "lost": 5,
    "power": 5,
    "win": 14,
    "play": 16,
    "mines": 5,
    "game": 10,
    "ship": 5,
    "dsb": 6,
    "kill": 16,
    "join": 8,
    "bot": 5,
    "team": 13,
    "today": 5,
    "usa": 6,
    "great": 7,
    "person": 5,
    "work": 5,
    "place": 6,
    "challenge": 5,
    "mad": 6,
    "ball": 9,
    "job": 5,
    "battle": 5,
    "people": 17,
    "god": 6,
    "freespirit": 5,
    "die": 6,
    "money": 5,
    "time": 10,
    "beef": 6,
    "jav": 7,
    "guys": 7,
    "autism": 5,
    "3": 6,
    "sting": 5,
    "killing": 5,
    "love": 6,
    "black": 5,
    "shit": 5,
    "eat": 5,
    "games": 5,
    "played": 5,
    "high": 5
}