{
    "lol": 61,
    "lure": 8,
    "strays": 6,
    "wrong": 15,
    "ya": 16,
    "throwdown": 26,
    "@": 24,
    "150k": 7,
    "idiets": 5,
    "ez": 5,
    "pretend": 5,
    "deal": 7,
    "boost": 6,
    "face": 12,
    "gey": 7,
    "guys": 45,
    "losing": 5,
    "literally": 5,
    "moon": 7,
    "pain": 7,
    "send": 9,
    "high": 9,
    "dont": 38,
    "throw": 7,
    "americans": 7,
    "1": 10,
    "surgery": 5,
    ":p": 5,
    "learned": 5,
    "love": 6,
    "time": 32,
    "fact": 10,
    "real": 16,
    "isnt": 10,
    "culture": 5,
    "feel": 11,
    "": 64,
    "pro": 5,
    "trump": 7,
    "like,": 11,
    "food": 5,
    "talk": 5,
    "mad": 8,
    "shit": 15,
    "entire": 10,
    "double": 7,
    "money": 10,
    "doesnt": 15,
    "change": 5,
    "man": 5,
    "cos": 16,
    "win": 6,
    "airduster": 10,
    "single": 11,
    "life": 9,
    "concept": 5,
    "gotta": 6,
    "ppl": 11,
    "100": 8,
    "low": 14,
    "didnt": 9,
    "global": 6,
    "year": 12,
    "based": 8,
    "making": 5,
    "woman": 6,
    "tho": 8,
    "good": 12,
    "ass": 6,
    "gaza": 6,
    "pls": 8,
    "it,": 8,
    "support": 9,
    "years": 9,
    "big": 7,
    "age": 7,
    "-": 8,
    "crowd": 5,
    "90s": 5,
    "basically": 9,
    "play": 12,
    "actual": 14,
    "game": 5,
    "20": 5,
    "worth": 6,
    "staff": 6,
    "racist": 15,
    "allowed": 7,
    "truth": 15,
    "problem": 5,
    "cross": 5,
    "remain": 5,
    "die": 6,
    "difference": 5,
    "conditions": 7,
    "people": 54,
    "save": 6,
    "player": 5,
    "ive": 5,
    "loss": 5,
    "gonna": 8,
    "team": 7,
    "person": 7,
    "lose": 5,
    "thing": 7,
    "fk": 15,
    "flag": 6,
    "2": 9,
    "set": 5,
    "stuff": 5,
    "deserve": 5,
    "free": 13,
    "zone": 5,
    "biden": 6,
    "anger": 7,
    "things": 5,
    "remember": 6,
    "felt": 5,
    "day": 14,
    "shot": 6,
    "american": 10,
    "women": 7,
    "state": 7,
    "kind": 9,
    "true": 8,
    "listen": 6,
    "half": 6,
    "bad": 11,
    "jesus": 13,
    "total": 6,
    "data": 11,
    "4": 5,
    "list": 8,
    "ai": 12,
    "nice": 5,
    "white": 8,
    "music": 5,
    "hate": 8,
    "0": 5,
    "times": 7,
    "50%": 7,
    "mind": 6,
    "evil": 9,
    "tbh": 6,
    "machine": 6,
    "learning": 5,
    "versus": 7,
    "public": 8,
    "live": 6,
    "animals": 6,
    "america": 6,
    "eat": 5,
    "today": 5,
    "level": 7,
    "wealth": 8,
    "billion": 7,
    "power": 7,
    "human": 8,
    "poor": 5,
    "5": 6,
    "3": 8,
    "round": 5,
    "population": 5,
    "control": 8,
    "president": 5,
    "kid": 5,
    "dog": 6,
    "kids": 5,
    "century": 6,
    "main": 5,
    "it.": 5,
    "players": 8,
    "higher": 5,
    "understand": 5,
    "fbi": 5,
    "newbs": 5,
    "enjoy": 6,
    "dogs": 5,
    "aliens": 5,
    "china": 8,
    "called": 7,
    "pay": 7,
    "reality": 6,
    "word": 6,
    "work": 6,
    "killed": 8,
    "hamas": 5,
    "ideas": 9,
    "purpose": 5,
    "10": 5,
    "math": 7,
    "laura": 6,
    "cat": 5,
    "negative": 6,
    "grounding": 5,
    "rods": 5,
    "month": 5
}